nimmy/__init__.py
nimmy/__main__.py
nimmy/display.py
nimmy/game.py
nimmy-0.1.3.dist-info/METADATA
nimmy-0.1.3.dist-info/WHEEL
nimmy-0.1.3.dist-info/entry_points.txt
nimmy-0.1.3.dist-info/top_level.txt
nimmy-0.1.3.dist-info/RECORD
